odoo/addons/ai_oca_bridge/README.rst
odoo/addons/ai_oca_bridge/__init__.py
odoo/addons/ai_oca_bridge/__manifest__.py
odoo/addons/ai_oca_bridge/controllers/__init__.py
odoo/addons/ai_oca_bridge/controllers/ai.py
odoo/addons/ai_oca_bridge/data/ir_module_category.xml
odoo/addons/ai_oca_bridge/i18n/ai_oca_bridge.pot
odoo/addons/ai_oca_bridge/i18n/es.po
odoo/addons/ai_oca_bridge/i18n/es_VE.po
odoo/addons/ai_oca_bridge/i18n/it.po
odoo/addons/ai_oca_bridge/i18n/pt_BR.po
odoo/addons/ai_oca_bridge/models/__init__.py
odoo/addons/ai_oca_bridge/models/ai_bridge.py
odoo/addons/ai_oca_bridge/models/ai_bridge_execution.py
odoo/addons/ai_oca_bridge/models/ai_bridge_thread.py
odoo/addons/ai_oca_bridge/models/base.py
odoo/addons/ai_oca_bridge/models/mail_thread.py
odoo/addons/ai_oca_bridge/readme/CONFIGURE.md
odoo/addons/ai_oca_bridge/readme/CONTEXT.md
odoo/addons/ai_oca_bridge/readme/CONTRIBUTORS.md
odoo/addons/ai_oca_bridge/readme/DESCRIPTION.md
odoo/addons/ai_oca_bridge/readme/ROADMAP.md
odoo/addons/ai_oca_bridge/readme/USAGE.md
odoo/addons/ai_oca_bridge/security/ir.model.access.csv
odoo/addons/ai_oca_bridge/security/security.xml
odoo/addons/ai_oca_bridge/static/description/icon.png
odoo/addons/ai_oca_bridge/static/description/icon.svg
odoo/addons/ai_oca_bridge/static/description/index.html
odoo/addons/ai_oca_bridge/static/src/chatter_ai_registry.esm.js
odoo/addons/ai_oca_bridge/static/src/components/chatter/chatter.esm.js
odoo/addons/ai_oca_bridge/static/src/components/chatter_topbar/chatter_topbar.xml
odoo/addons/ai_oca_bridge/static/src/components/chatter_topbar_ai/chatter_topbar_ai.esm.js
odoo/addons/ai_oca_bridge/static/src/components/chatter_topbar_ai/chatter_topbar_ai.xml
odoo/addons/ai_oca_bridge/static/src/components/chatter_topbar_ai_item/chatter_topbar_ai_item.esm.js
odoo/addons/ai_oca_bridge/static/src/components/chatter_topbar_ai_item/chatter_topbar_ai_item.xml
odoo/addons/ai_oca_bridge/static/tests/mock_server/define_ai_models.esm.js
odoo_addon_ai_oca_bridge-18.0.2.0.0.2.dist-info/METADATA
odoo_addon_ai_oca_bridge-18.0.2.0.0.2.dist-info/WHEEL
odoo_addon_ai_oca_bridge-18.0.2.0.0.2.dist-info/top_level.txt
odoo_addon_ai_oca_bridge-18.0.2.0.0.2.dist-info/RECORD
