Metadata-Version: 2.1
Name: odoo-addon-ai_oca_bridge
Version: 18.0.2.0.0.2
Requires-Python: >=3.10
Requires-Dist: odoo==18.0.*
Summary: Makes a basic configuration to be used as bridge with external AI systems
Home-page: https://github.com/OCA/ai
License: AGPL-3
Author: Dixmit,Odoo Community Association (OCA)
Author-email: support@odoo-community.org
Classifier: Programming Language :: Python
Classifier: Framework :: Odoo
Classifier: Framework :: Odoo :: 18.0
Classifier: License :: OSI Approved :: GNU Affero General Public License v3
Classifier: Development Status :: 4 - Beta
